LICENSE.txt
README.md
setup.cfg
setup.py
my_methods/__init__.py
my_methods/choose_best_classifier.py
my_methods/choose_best_regressor.py
my_methods/choose_optimal_number_of_clusters.py
my_methods/get_cross_validation.py
my_methods/get_internshala_Internship.py
my_methods/initialize_weights.py
my_methods/login_to_internshala.py
my_methods/matrix_multiplication_without_numpy.py
my_methods/my_backward_propagation.py
my_methods/my_cap_curve.py
my_methods/my_dummy_variable_creator.py
my_methods/my_global_variables.py
my_methods/my_roc_curve.py
my_methods/plot_text.py
my_methods/print_model_results.py
my_methods/sgd_neural_net.py
my_methods/transpose_of_matrix_without_numpy.py
my_methods/visualise_classifier_performance.py
my_methods.egg-info/PKG-INFO
my_methods.egg-info/SOURCES.txt
my_methods.egg-info/dependency_links.txt
my_methods.egg-info/top_level.txt