Metadata-Version: 2.1
Name: my-methods
Version: 0.0.7
Summary: my_methods
Home-page: https://github.com/noushadkhan01/my_methods
Author: Noushad Khan
Author-email: noushadkhan1994@gmail.com
License: UNKNOWN
Platform: UNKNOWN
Classifier: Programming Language :: Python :: 3
Classifier: License :: OSI Approved :: MIT License
Classifier: Operating System :: OS Independent
Requires-Python: >=3.6
